exlog/__init__.py
exlog/core.py
exlog/saver.py
exlog/loggers/__init__.py
exlog/loggers/default_logger.py
exlog/loggers/lightgbm_logger.py
exlog/loggers/sklearn_logger.py
exlog/loggers/torch_tensorflow_logger.py
exlog/loggers/xgboost_logger.py
exlog/test/Tensorflow/tensorflow_feedforward_test.py
exlog/test/lightgbm/lightgbm_binary_classification_test.py
exlog/test/lightgbm/lightgbm_multiclass_classification_test.py
exlog/test/lightgbm/lightgbm_regression_test.py
exlog/test/sklearn/Kernel_sklearn_test.py
exlog/test/sklearn/Linear_sklearn_test.py
exlog/test/sklearn/Tree_sklearn_test.py
exlog/test/torch/torch_test.py
exlog/test/unified_test/unified_test.py
exlog/test/xgboost/xgboost_binary_classification_test.py
exlog/test/xgboost/xgboost_multiclass_classification_test.py
exlog/test/xgboost/xgboost_regression_test.py
mlexlog-0.1.4.dist-info/METADATA
mlexlog-0.1.4.dist-info/WHEEL
mlexlog-0.1.4.dist-info/top_level.txt
mlexlog-0.1.4.dist-info/RECORD
